cradlebio/__init__.py
cradlebio/alphafold.py
cradlebio/auth.py
cradlebio/golden_path.py
cradlebio/snippet.py
cradlebio/tst.py
cradlebio/tst2.py
cradlebio/watch.py
cradlebio-1.0.0.dist-info/LICENSE
cradlebio-1.0.0.dist-info/WHEEL
cradlebio-1.0.0.dist-info/METADATA
cradlebio-1.0.0.dist-info/RECORD
