Metadata-Version: 2.1
Name: cradlebio
Version: 1.0.0
Summary: Client for Cradle's Alphafold-as-a-service
License: Apache 2.0
Author: Cradle Bio
Author-email: info@cradle.bio
Requires-Python: >=3.7.2,<4.0.0
Classifier: License :: Other/Proprietary License
Classifier: Programming Language :: Python :: 3
Classifier: Programming Language :: Python :: 3.8
Classifier: Programming Language :: Python :: 3.9
Classifier: Programming Language :: Python :: 3.10
Classifier: Programming Language :: Python :: 3.11
Requires-Dist: Sphinx (>=5.1.1,<6.0.0)
Requires-Dist: biopython (>=1.70,<2.0)
Requires-Dist: fsspec[gcs] (>=2022.7.1,<2023.0.0)
Requires-Dist: google-api-python-client (>=2.42.0,<3.0.0)
Requires-Dist: google-auth (>=2.6,<3.0)
Requires-Dist: google-cloud-firestore (>=2.4.0,<3.0.0)
Requires-Dist: google-cloud-storage (>=2.2.1,<3.0.0)
Requires-Dist: importlib_metadata (>=4.12.0,<5.0.0)
Requires-Dist: myst-parser (>=0.18.0,<0.19.0)
Requires-Dist: packaging (>=21.3,<22.0)
Requires-Dist: sphinxcontrib-fulltoc (>=1.2.0,<2.0.0)
Requires-Dist: tqdm (>=4.64.0,<5.0.0)
